nuqql_slixmppd/__init__.py
nuqql_slixmppd/client.py
nuqql_slixmppd/main.py
nuqql_slixmppd/server.py
nuqql_slixmppd-0.8.7.dist-info/licenses/LICENSE
nuqql_slixmppd-0.8.7.dist-info/METADATA
nuqql_slixmppd-0.8.7.dist-info/WHEEL
nuqql_slixmppd-0.8.7.dist-info/entry_points.txt
nuqql_slixmppd-0.8.7.dist-info/top_level.txt
nuqql_slixmppd-0.8.7.dist-info/RECORD
