Metadata-Version: 2.4
Name: nuqql-slixmppd
Version: 0.8.7
Summary: XMPP client network daemon using slixmpp
Home-page: https://github.com/hwipl/nuqql-slixmppd
Author: hwipl
Author-email: nuqql-slixmppd@hwipl.net
License: MIT
Classifier: Programming Language :: Python :: 3
Classifier: License :: OSI Approved :: MIT License
Requires-Python: >=3.7
License-File: LICENSE
Requires-Dist: nuqql-based~=0.3.0
Requires-Dist: slixmpp~=1.12.0
Dynamic: author
Dynamic: author-email
Dynamic: classifier
Dynamic: description
Dynamic: description-content-type
Dynamic: home-page
Dynamic: license
Dynamic: license-file
Dynamic: requires-dist
Dynamic: requires-python
Dynamic: summary
